qdflow/__init__.py
qdflow/generate.py
qdflow/py.typed
qdflow/physics/__init__.py
qdflow/physics/noise.py
qdflow/physics/simulation.py
qdflow/util/__init__.py
qdflow/util/distribution.py
qdflow-1.0.2.dist-info/licenses/LICENSE
qdflow-1.0.2.dist-info/METADATA
qdflow-1.0.2.dist-info/WHEEL
qdflow-1.0.2.dist-info/top_level.txt
qdflow-1.0.2.dist-info/RECORD
